tesser_api_sdk-1.0.0.dist-info/licenses/LICENSE
tesserapiv1/__init__.py
tesserapiv1/api_helper.py
tesserapiv1/configuration.py
tesserapiv1/tesserapiv_1_client.py
tesserapiv1/controllers/__init__.py
tesserapiv1/controllers/accounts_controller.py
tesserapiv1/controllers/base_controller.py
tesserapiv1/controllers/counterparties_controller.py
tesserapiv1/controllers/currencies_controller.py
tesserapiv1/controllers/experimental_controller.py
tesserapiv1/controllers/health_controller.py
tesserapiv1/controllers/networks_controller.py
tesserapiv1/controllers/payments_controller.py
tesserapiv1/controllers/tenants_controller.py
tesserapiv1/controllers/treasury_controller.py
tesserapiv1/exceptions/__init__.py
tesserapiv1/exceptions/api_exception.py
tesserapiv1/http/__init__.py
tesserapiv1/http/http_call_back.py
tesserapiv1/http/http_client_provider.py
tesserapiv1/http/http_method_enum.py
tesserapiv1/http/http_request.py
tesserapiv1/http/http_response.py
tesserapiv1/http/proxy_settings.py
tesserapiv1/http/auth/__init__.py
tesserapiv1/http/auth/o_auth_2.py
tesserapiv1/models/__init__.py
tesserapiv1/models/account.py
tesserapiv1/models/account_list_item.py
tesserapiv1/models/account_list_response.py
tesserapiv1/models/account_response.py
tesserapiv1/models/account_safe.py
tesserapiv1/models/balance_status_1_enum.py
tesserapiv1/models/balance_status_enum.py
tesserapiv1/models/classification_7_enum.py
tesserapiv1/models/classification_enum.py
tesserapiv1/models/counterparty.py
tesserapiv1/models/counterparty_list_response.py
tesserapiv1/models/counterparty_response.py
tesserapiv1/models/create_bank_request.py
tesserapiv1/models/create_bank_response.py
tesserapiv1/models/create_counterparty_request.py
tesserapiv1/models/create_counterparty_response.py
tesserapiv1/models/create_deposit_request.py
tesserapiv1/models/create_payment_request.py
tesserapiv1/models/create_tenant_request.py
tesserapiv1/models/create_tenant_response.py
tesserapiv1/models/create_wallet_request.py
tesserapiv1/models/create_wallet_response.py
tesser_api_sdk-1.0.0.dist-info/METADATA
tesser_api_sdk-1.0.0.dist-info/WHEEL
tesser_api_sdk-1.0.0.dist-info/top_level.txt
tesser_api_sdk-1.0.0.dist-info/RECORD
