Metadata-Version: 2.4
Name: tesser-api-sdk
Version: 1.0.0
Summary: Tesser API SDK
Author-email: Muhammad Rafay <muhammad.rafay@apimatic.io>
Project-URL: Documentation, https://docs.tessera.consensys.io/Reference/TesseraAPI
Requires-Python: >=3.7
License-File: LICENSE
Requires-Dist: apimatic-core>=0.2.24,~=0.2.0
Requires-Dist: apimatic-core-interfaces>=0.1.8,~=0.1.0
Requires-Dist: apimatic-requests-client-adapter>=0.1.10,~=0.1.0
Requires-Dist: python-dotenv<2.0,>=0.21
Provides-Extra: testutils
Requires-Dist: pytest>=7.2.2; extra == "testutils"
Dynamic: license-file
